sentior_platform/__init__.py
sentior_platform/generated/__init__.py
sentior_platform/generated/collections.py
sentior_platform/generated/entitlements.py
sentior_platform/generated/events.py
sentior_platform/generated/version.py
sentior_platform_sdk-0.1.100.dist-info/METADATA
sentior_platform_sdk-0.1.100.dist-info/WHEEL
sentior_platform_sdk-0.1.100.dist-info/top_level.txt
sentior_platform_sdk-0.1.100.dist-info/RECORD
