Metadata-Version: 2.4
Name: sentior-platform-sdk
Version: 0.1.100
Summary: Internal Sentior Platform SDK
Author: Sentior
Dynamic: author
Dynamic: summary
